chick/Spider.py
chick/__init__.py
WdSpider-0.0.3.dist-info/METADATA
WdSpider-0.0.3.dist-info/WHEEL
WdSpider-0.0.3.dist-info/top_level.txt
WdSpider-0.0.3.dist-info/RECORD
