Metadata-Version: 2.1
Name: WdSpider
Version: 0.0.3
Summary: This is my bag
Home-page: https://gitee.com/song-mingyu-a/p9-operation
Author: SongMingYu
Author-email: 1449065358@qq.com
